[
  {
    "name": "#DIY",
    "members": [
      "Tommaso Ciampa",
      "Johnny Gargano"
    ],
    "subs": [],
    "category": "WWE"
  },
  {
    "name": "3 Minute Warning",
    "members": [
      "Jamal",
      "Rosey"
    ],
    "subs": [],
    "category": "WWE"
  },
  {
    "name": "AJ Lee & CM Punk",
    "members": [
      "AJ Lee",
      "CM Punk"
    ],
    "subs": [],
    "category": "WWE"
  },
  {
    "name": "AJ Lee '15 & CM Punk",
    "members": [
      "AJ Lee '15",
      "CM Punk"
    ],
    "subs": [],
    "category": "WWE"
  },
  {
    "name": "AJ Styles & Dragon Lee",
    "members": [
      "AJ Styles",
      "Dragon Lee"
    ],
    "subs": [],
    "category": "WWE"
  },
  {
    "name": "Alexa Bliss & Charlotte Flair",
    "members": [
      "Alexa Bliss",
      "Charlotte Flair"
    ],
    "subs": [],
    "category": "WWE"
  },
  {
    "name": "Alpha Academy",
    "members": [
      "Chad Gable",
      "Otis",
      "Maxxine Dupri"
    ],
    "subs": [],
    "category": "WWE"
  },
  {
    "name": "American Made",
    "members": [
      "Chad Gable",
      "Brutus Creed",
      "Julius Creed",
      "Ivy Nile"
    ],
    "subs": [],
    "category": "WWE"
  },
  {
    "name": "Brothers of Destruction, The",
    "members": [
      "Undertaker",
      "Kane"
    ],
    "subs": [],
    "category": "WWE"
  },
  {
    "name": "Chelsea Green and The Secret Hervice",
    "members": [
      "Chelsea Green",
      "Piper Niven",
      "Alba Fyre"
    ],
    "subs": [],
    "category": "WWE"
  },
  {
    "name": "Culling, The",
    "members": [
      "Lexis King",
      "Shawn Spears",
      "Lola Vice"
    ],
    "subs": [],
    "category": "WWE"
  },
  {
    "name": "D Generation X",
    "members": [
      "Triple H",
      "Shawn Michaels",
      "Road Dogg",
      "Badd Ass Billy Gunn",
      "X-Pac"
    ],
    "subs": [],
    "category": "WWE"
  },
  {
    "name": "D Generation X (Classic)",
    "members": [
      "Hunter Hearst Helmsley",
      "Shawn Michaels",
      "Chyna",
      "Road Dogg Jesse James",
      "X-Pac"
    ],
    "subs": [],
    "category": "WWE"
  },
  {
    "name": "Dudley Boyz, The",
    "members": [
      "Bubba Ray Dudley",
      "D Von Dudley"
    ],
    "subs": [],
    "category": "WWE"
  },
  {
    "name": "Fatal Influence, The",
    "members": [
      "Jacy Jayne",
      "Jazmyn Nyx",
      "Fallon Henley"
    ],
    "subs": [],
    "category": "WWE"
  },
  {
    "name": "Fraxiom",
    "members": [
      "Nathan Frazer",
      "Axiom"
    ],
    "subs": [],
    "category": "WWE"
  },
  {
    "name": "Hank and Tank",
    "members": [
      "Hank Walker",
      "Tank Ledger"
    ],
    "subs": [],
    "category": "WWE"
  },
  {
    "name": "Hart Foundation, The",
    "members": [
      "Bret Hit Man Hart",
      "Jim The Anvil Neidhart",
      "British Bulldog"
    ],
    "subs": [],
    "category": "WWE"
  },
  {
    "name": "Headbangers, The",
    "members": [
      "Mosh",
      "Thrasher"
    ],
    "subs": [],
    "category": "WWE"
  },
  {
    "name": "Islanders, The",
    "members": [
      "Haku",
      "Tama"
    ],
    "subs": [],
    "category": "WWE"
  },
  {
    "name": "Judgement Day, The",
    "members": [
      "Finn Balor",
      "JD McDonagh",
      "Dirty Dominik Mysterio",
      "Raquel Rodriguez",
      "Liv Morgan"
    ],
    "subs": [],
    "category": "WWE"
  },
  {
    "name": "Kabuki Warriors",
    "members": [
      "Asuka",
      "Kairi Sane"
    ],
    "subs": [],
    "category": "WWE"
  },
  {
    "name": "Latino World Order",
    "members": [
      "Eddie Guerrero",
      "Dragon Lee",
      "Joaquin Wilde",
      "Cruz Del Toro",
      "Sensational Sherri"
    ],
    "subs": [],
    "category": "WWE"
  },
  {
    "name": "Legado Del Fantasma",
    "members": [
      "Santos Escobar",
      "Cruz Del Toro",
      "Joaquin Wilde"
    ],
    "subs": [],
    "category": "WWE"
  },
  {
    "name": "MFT",
    "members": [
      "Solo Sikoa",
      "Tama Tonga",
      "Tonga Loa",
      "JC Mateo",
      "Talla Tonga"
    ],
    "subs": [],
    "category": "WWE"
  },
  {
    "name": "Miz, The and Maryse",
    "members": [
      "Miz, The",
      "Maryse"
    ],
    "subs": [],
    "category": "WWE"
  },
  {
    "name": "Motor City Machine Guns",
    "members": [
      "Chris Sabin"
    ],
    "subs": [],
    "category": "WWE"
  },
  {
    "name": "New Age Outlaws",
    "members": [
      "Road Dogg",
      "Badd Ass Billy Gunn"
    ],
    "subs": [],
    "category": "WWE"
  },
  {
    "name": "New Day, The",
    "members": [
      "Kofi Kingston",
      "Xavier Woods",
      "Big E"
    ],
    "subs": [],
    "category": "WWE"
  },
  {
    "name": "New World Order",
    "members": [
      "Hollywood Hogan",
      "Scott Hall",
      "Kevin Nash",
      "Syxx"
    ],
    "subs": [],
    "category": "WWE"
  },
  {
    "name": "No Quarter Catch Crew",
    "members": [
      "Charlie Dempsey",
      "Myles Borne",
      "Tavion Heights",
      "Wren Sinclair"
    ],
    "subs": [],
    "category": "WWE"
  },
  {
    "name": "Pretty Deadly",
    "members": [
      "Elton Prince",
      "Kit Wilson"
    ],
    "subs": [],
    "category": "WWE"
  },
  {
    "name": "Rhiyo",
    "members": [
      "Rhea Ripley",
      "IYO SKY"
    ],
    "subs": [],
    "category": "WWE"
  },
  {
    "name": "Steiner Brothers, The",
    "members": [
      "Rick Steiner",
      "Scott Steiner '93"
    ],
    "subs": [],
    "category": "WWE"
  },
  {
    "name": "Street Profits, The",
    "members": [
      "Angelo Dawkins",
      "Montez Ford",
      "B-Fab"
    ],
    "subs": [],
    "category": "WWE"
  },
  {
    "name": "Usos, The",
    "members": [
      "Jey Uso",
      "Jimmy Uso"
    ],
    "subs": [],
    "category": "WWE"
  },
  {
    "name": "Vision, The",
    "members": [
      "Solo Sikoa",
      "JC Mateo",
      "Jacob Fatu",
      "Talla Tonga",
      "Tonga Loa"
    ],
    "subs": [],
    "category": "WWE"
  },
  {
    "name": "War Raiders, The",
    "members": [
      "Ivar",
      "Erik"
    ],
    "subs": [],
    "category": "WWE"
  },
  {
    "name": "Wild Samoans, The",
    "members": [
      "Afa",
      "Sika"
    ],
    "subs": [],
    "category": "WWE"
  },
  {
    "name": "Wyatt Sicks",
    "members": [
      "Uncle Howdy",
      "Erick Rowan",
      "Joe Gacy",
      "Dexter Lumis",
      "Hector Flores"
    ],
    "subs": [],
    "category": "WWE"
  },
  {
    "name": "Visions, The",
    "members": [
      "Logan Paul",
      "Austin Theory",
      "Jake Paul",
      "IShowSpeed"
    ],
    "subs": [],
    "category": "WWE"
  },
  {
    "name": "The CIA",
    "members": [
      "Aquaman",
      "Black Panther",
      "Batman",
      "Robin",
      "Green Arrow"
    ],
    "subs": [],
    "category": "CUSTOM"
  },
  {
    "name": "The Crew",
    "members": [
      "Green Ranger",
      "Black Ranger",
      "Blue Ranger",
      "Red Ranger"
    ],
    "subs": [],
    "category": "CUSTOM"
  },
  {
    "name": "The Dangerous Alliance",
    "members": [
      "Catwoman",
      "Death",
      "Hela",
      "Poison Ivy"
    ],
    "subs": [],
    "category": "CUSTOM"
  },
  {
    "name": "The Queens",
    "members": [
      "Sleeping Beauty",
      "Snow White",
      "Tangled Rapunzel",
      "Tinkerbell"
    ],
    "subs": [],
    "category": "CUSTOM"
  },
  {
    "name": "The Mega Powers",
    "members": [
      "Kimberly Hart",
      "Rocky DeSantos",
      "Tommy Oliver"
    ],
    "subs": [],
    "category": "WWE"
  },
  {
    "name": "The Rangers",
    "members": [
      "Adam Park",
      "Aisha Campbell",
      "Billy Cranston"
    ],
    "subs": [],
    "category": "WWE"
  },
  {
    "name": "Power and Glory",
    "members": [
      "Goldar",
      "Lord Zedd",
      "Scorpina"
    ],
    "subs": [],
    "category": "WWE"
  },
  {
    "name": "The Undead",
    "members": [
      "Carl Grimes",
      "Daryl Dixon",
      "Negan"
    ],
    "subs": [],
    "category": "WWE"
  },
  {
    "name": "The Acolytes",
    "members": [
      "Rick Grimes",
      "Shane Walsh",
      "Governor, The"
    ],
    "subs": [],
    "category": "WWE"
  },
  {
    "name": "The Agents",
    "members": [
      "Maggie Rhee",
      "Beta"
    ],
    "subs": [],
    "category": "WWE"
  },
  {
    "name": "New Catch Republic",
    "members": [
      "Abraham Lincoln",
      "Barack Obama",
      "Bill Clinton"
    ],
    "subs": [],
    "category": "WWE"
  },
  {
    "name": "The Republic",
    "members": [
      "Bernie Sanders",
      "Cleopatra",
      "Donald Trump"
    ],
    "subs": [],
    "category": "WWE"
  },
  {
    "name": "The Corporation",
    "members": [
      "George W. Bush",
      "Hillary Clinton",
      "Jill Biden"
    ],
    "subs": [],
    "category": "WWE"
  },
  {
    "name": "The Patriots",
    "members": [
      "Joe Biden",
      "John F. Kennedy",
      "Laura Bush"
    ],
    "subs": [],
    "category": "WWE"
  },
  {
    "name": "The Fatal Influence",
    "members": [
      "Ninja",
      "Pokimane",
      "Sketch"
    ],
    "subs": [],
    "category": "WWE"
  },
  {
    "name": "The Job Squad",
    "members": [
      "FaZe Adapt",
      "Ironmouse",
      "Jynxi"
    ],
    "subs": [],
    "category": "WWE"
  },
  {
    "name": "The Boom Squad",
    "members": [
      "Adin Ross",
      "Amouranth",
      "Caseoh"
    ],
    "subs": [],
    "category": "WWE"
  },
  {
    "name": "The Hit Squad",
    "members": [
      "Cinna",
      "Emiru",
      "Faze Rug"
    ],
    "subs": [],
    "category": "WWE"
  },
  {
    "name": "The Athlete (Attack)",
    "members": [
      "Ghostface",
      "Sidney Prescott"
    ],
    "subs": [],
    "category": "WWE"
  },
  {
    "name": "3MB",
    "members": [
      "Donatello",
      "Leonardo",
      "Michelangelo"
    ],
    "subs": [],
    "category": "WWE"
  },
  {
    "name": "A-Town Down Under",
    "members": [
      "Raphael",
      "April O'Neil",
      "Casey Jones"
    ],
    "subs": [],
    "category": "WWE"
  },
  {
    "name": "Absolution",
    "members": [
      "Bebop",
      "Rocksteady",
      "Shredder, The"
    ],
    "subs": [],
    "category": "WWE"
  },
  {
    "name": "Air Boom",
    "members": [
      "Fred Flintstone",
      "Wilma Flintstone",
      "Barney Rubble"
    ],
    "subs": [],
    "category": "WWE"
  },
  {
    "name": "The Alliance",
    "members": [
      "Pebbles Flintstone",
      "Bamm-Bamm Rubble"
    ],
    "subs": [],
    "category": "WWE"
  },
  {
    "name": "The United Kingdom",
    "members": [
      "Super Mario",
      "Luigi"
    ],
    "subs": [],
    "category": "WWE"
  },
  {
    "name": "The Good Girls",
    "members": [
      "Anna",
      "Ariel",
      "Aurora"
    ],
    "subs": [],
    "category": "WWE"
  },
  {
    "name": "The Naughty Girls",
    "members": [
      "Belle",
      "Cinderella",
      "Frozen Elsa"
    ],
    "subs": [],
    "category": "WWE"
  },
  {
    "name": "The Spitfire Warriors",
    "members": [
      "Kitana",
      "Mileena",
      "Nitara"
    ],
    "subs": [],
    "category": "WWE"
  },
  {
    "name": "The Anarchists",
    "members": [
      "Fred Jones",
      "Velma Dinkley"
    ],
    "subs": [],
    "category": "WWE"
  },
  {
    "name": "The Empire of Pain 1",
    "members": [
      "Abyss",
      "Dusty Rhodes",
      "Brock Lesnar",
      "Cody Rhodes",
      "Doink The Clown"
    ],
    "subs": [],
    "category": "CUSTOM"
  },
  {
    "name": "The Empire of Pain 2",
    "members": [
      "Kenny Lopez",
      "Rey Mysterio",
      "Lita",
      "Adapt",
      "Rug"
    ],
    "subs": [],
    "category": "CUSTOM"
  },
  {
    "name": "The Empire of Pain 3",
    "members": [
      "Malachi The Mad",
      "Hunter Rhyn Trax",
      "Princess Victoria",
      "Velvet Mcintyre",
      "Tank Bryson"
    ],
    "subs": [],
    "category": "CUSTOM"
  },
  {
    "name": "The Empire of Pain 4",
    "members": [
      "Woody",
      "Buzz Lightyear",
      "Sandman, The",
      "Superman",
      "Supergirl"
    ],
    "subs": [],
    "category": "CUSTOM"
  },
  {
    "name": "The Empire of Pain 5",
    "members": [
      "Zelina Vega (Player/Streamer)",
      "Sandra Lopez (Player/Streamer)",
      "Undertaker '03",
      "Jack Talos",
      "John Cena"
    ],
    "subs": [],
    "category": "CUSTOM"
  },
  {
    "name": "The Empire of Pain 6",
    "members": [
      "Bron Breaker",
      "Bronson Reed",
      "Trish Stratus",
      "Rob Van Dam",
      "Mark Henry"
    ],
    "subs": [],
    "category": "CUSTOM"
  },
  {
    "name": "The Empire of Pain 7",
    "members": [
      "Moana",
      "Mulan",
      "Kurt Angle",
      "Scorpion",
      "Sub Zero"
    ],
    "subs": [],
    "category": "CUSTOM"
  },
  {
    "name": "The Empire of Pain 8",
    "members": [
      "Chuck Norris",
      "Sam Larusso",
      "Daniel Larusso",
      "Robby Keen",
      "Miguel Diaz"
    ],
    "subs": [],
    "category": "CUSTOM"
  },
  {
    "name": "The Empire of Pain 9",
    "members": [
      "Freddy Krueger",
      "Je Von Evans",
      "Chucky",
      "Tiffany Valentine",
      "Ghostface"
    ],
    "subs": [],
    "category": "CUSTOM"
  },
  {
    "name": "The Empire of Pain 10",
    "members": [
      "Batista",
      "Cappuccino Jones",
      "Danny Lopez"
    ],
    "subs": [],
    "category": "CUSTOM"
  }
]